flexible_classifier/__init__.py
flexible_classifier/classifier.py
flexible_classifier-0.0.11.dist-info/METADATA
flexible_classifier-0.0.11.dist-info/WHEEL
flexible_classifier-0.0.11.dist-info/licenses/LICENSE
flexible_classifier-0.0.11.dist-info/RECORD
