Metadata-Version: 2.3
Name: flexible_classifier
Version: 0.0.11
Summary: Classifier pipeline that can be used to train and evaluate classification models on various datasets
Project-URL: Homepage, https://github.com/GameRuiner/classifier-pipeline
Project-URL: Issues, https://github.com/GameRuiner/classifier-pipeline/issues
Author-email: Marko Golovko <markgolovko@gmail.com>
License-File: LICENSE
Classifier: License :: OSI Approved :: MIT License
Classifier: Operating System :: OS Independent
Classifier: Programming Language :: Python :: 3
Requires-Python: >=3.8
